AUTHORS
LICENSE
MANIFEST.in
README.creole
setup.py
src/django_xslt.egg-info/PKG-INFO
src/django_xslt.egg-info/SOURCES.txt
src/django_xslt.egg-info/dependency_links.txt
src/django_xslt.egg-info/top_level.txt
src/djangoxslt/__init__.py
src/djangoxslt/xslt/__init__.py
src/djangoxslt/xslt/engine.py
src/djangoxslt/xslt/managers.py
src/djangoxslt/xslt/models.py
src/djangoxslt/xslt/testhelp.py
src/djangoxslt/xslt/tests.py
src/djangoxslt/xslt/urls.py
src/djangoxslt/xslt/views.py