Metadata-Version: 1.0
Name: django-xslt
Version: 0.4.5
Summary: an XSLT template system for Django
Home-page: http://github.com/woome/django-xslt
Author: Nic Ferrier
Author-email: nic@woome.com
License: BSD
Download-URL: http://github.com/woome/django-xslt/downloads
Platform: unix
Classifier: Development Status :: 3 - Alpha
Classifier: Intended Audience :: Developers
Classifier: License :: OSI Approved :: BSD License
Classifier: Operating System :: OS Independent
Classifier: Programming Language :: Python
Classifier: Topic :: Utilities
Classifier: Topic :: Communications :: Email
